{
  "responseHeader":{
     "status":0,
     "QTime":9,
     "params":{
        "q":"*",
        "start":"0",
        "fq":"type:GAME AND system_type:nintendoswitch* AND product_code_txt:*",
        "sort":"sorting_title asc",
        "rows":"2",
        "wt":"json"
     }
  },
  "response":{
     "numFound":2,
     "start":0,
     "docs":[
        {
           "fs_id":"1360704",
           "change_date":"2019-02-15T16:59:35Z",
           "url":"/Giochi/Giochi-scaricabili-per-Nintendo-Switch/-Breakforcist-Battle-1360704.html",
           "type":"GAME",
           "dates_released_dts":[
              "2018-04-12T00:00:00Z"
           ],
           "club_nintendo":false,
           "pretty_date_s":"12/04/2018",
           "play_mode_tv_mode_b":true,
           "play_mode_handheld_mode_b":true,
           "product_code_txt":[
              "HACPAK98A"
           ],
           "image_url_sq_s":"//cdn01.nintendo-europe.com/media/images/11_square_images/games_18/nintendo_switch_download_software/SQ_NSwitchDS_BreakforcistBattle_image500w.jpg",
           "deprioritise_b":false,
           "pg_s":"GAME",
           "gift_finder_detail_page_image_url_s":"//cdn01.nintendo-europe.com/media/images/11_square_images/games_18/nintendo_switch_download_software/SQ_NSwitchDS_BreakforcistBattle_gift_finder_detailpage.jpg",
           "compatible_controller":[
              "nintendoswitch_pro_controller"
           ],
           "image_url":"//cdn01.nintendo-europe.com/media/images/11_square_images/games_18/nintendo_switch_download_software/SQ_NSwitchDS_BreakforcistBattle_image500w.jpg",
           "originally_for_t":"HAC",
           "paid_subscription_required_b":false,
           "cloud_saves_b":false,
           "digital_version_b":true,
           "title_extras_txt":[
              "#Breakforcist Battle"
           ],
           "image_url_h2x1_s":"//cdn01.nintendo-europe.com/media/images/10_share_images/games_15/nintendo_switch_download_software_1/H2x1_NSwitchDS_BreakforcistBattle_image500w.jpg",
           "system_type":[
              "nintendoswitch_downloadsoftware"
           ],
           "age_rating_sorting_i":3,
           "game_categories_txt":[
              "action",
              "arcade",
              "party",
              "puzzle"
           ],
           "play_mode_tabletop_mode_b":true,
           "publisher":"Lucid Sheep Games",
           "product_code_ss":[
              "HACPAK98A"
           ],
           "excerpt":"La salvezza della colazione dipende solo da te (e da 3 dei tuoi amici)!",
           "nsuid_txt":[
              "70010000003781"
           ],
           "date_from":"2018-04-12T00:00:00Z",
           "language_availability":[
              "english,french,german,italian,spanish"
           ],
           "price_has_discount_b":false,
           "price_discount_percentage_f":0.0,
           "title":"#Breakforcist Battle",
           "sorting_title":"#Breakforcist Battle",
           "gift_finder_carousel_image_url_s":"//cdn01.nintendo-europe.com/media/images/11_square_images/games_18/nintendo_switch_download_software/SQ_NSwitchDS_BreakforcistBattle_gift_finder_carousel.jpg",
           "wishlist_email_square_image_url_s":"//cdn01.nintendo-europe.com/media/images/11_square_images/games_18/nintendo_switch_download_software/SQ_NSwitchDS_BreakforcistBattle_square_image_wishlist.jpg",
           "players_to":4,
           "wishlist_email_banner640w_image_url_s":"//cdn01.nintendo-europe.com/media/images/10_share_images/games_15/nintendo_switch_download_software_1/H2x1_NSwitchDS_BreakforcistBattle_banner_image_wishlist_640w.jpg",
           "voice_chat_b":false,
           "playable_on_txt":[
              "HAC"
           ],
           "hits_i":300,
           "pretty_game_categories_txt":[
              "Arcade",
              "Azione",
              "Party",
              "Rompicapo"
           ],
           "gift_finder_wishlist_image_url_s":"//cdn01.nintendo-europe.com/media/images/11_square_images/games_18/nintendo_switch_download_software/SQ_NSwitchDS_BreakforcistBattle_gift_finder_wishlist.jpg",
           "switch_game_voucher_b":false,
           "game_category":[
              "action,arcade,party,puzzle"
           ],
           "system_names_txt":[
              "Nintendo Switch"
           ],
           "pretty_agerating_s":"3",
           "price_regular_f":7.99,
           "eshop_removed_b":false,
           "players_from":1,
           "age_rating_type":"pegi",
           "price_sorting_f":7.99,
           "price_lowest_f":7.99,
           "age_rating_value":"3",
           "physical_version_b":false,
           "wishlist_email_banner460w_image_url_s":"//cdn01.nintendo-europe.com/media/images/10_share_images/games_15/nintendo_switch_download_software_1/H2x1_NSwitchDS_BreakforcistBattle_banner_image_wishlist_460w.jpg",
           "_version_":1664595832055267341,
           "popularity":856
        },
        {
           "fs_id":"1496598",
           "change_date":"2019-02-15T16:59:35Z",
           "url":"/Giochi/Giochi-scaricabili-per-Nintendo-Switch/-KILLALLZOMBIES-1496598.html",
           "type":"GAME",
           "dates_released_dts":[
              "2019-01-24T00:00:00Z"
           ],
           "club_nintendo":false,
           "pretty_date_s":"24/01/2019",
           "play_mode_tv_mode_b":true,
           "play_mode_handheld_mode_b":true,
           "product_code_txt":[
              "HACPARXQA"
           ],
           "image_url_sq_s":"//cdn01.nintendo-europe.com/media/images/11_square_images/games_18/nintendo_switch_download_software/SQ_NSwitchDS_KillAllZombies_image500w.jpg",
           "deprioritise_b":false,
           "pg_s":"GAME",
           "gift_finder_detail_page_image_url_s":"//cdn01.nintendo-europe.com/media/images/11_square_images/games_18/nintendo_switch_download_software/SQ_NSwitchDS_KillAllZombies_gift_finder_detailpage.jpg",
           "compatible_controller":[
              "nintendoswitch_pro_controller"
           ],
           "image_url":"//cdn01.nintendo-europe.com/media/images/11_square_images/games_18/nintendo_switch_download_software/SQ_NSwitchDS_KillAllZombies_image500w.jpg",
           "originally_for_t":"HAC",
           "paid_subscription_required_b":false,
           "cloud_saves_b":true,
           "digital_version_b":true,
           "title_extras_txt":[
              "#KILLALLZOMBIES"
           ],
           "image_url_h2x1_s":"//cdn01.nintendo-europe.com/media/images/10_share_images/games_15/nintendo_switch_download_software_1/H2x1_NSwitchDS_KillAllZombies_image500w.jpg",
           "system_type":[
              "nintendoswitch_downloadsoftware"
           ],
           "age_rating_sorting_i":16,
           "game_categories_txt":[
              "action",
              "shooter"
           ],
           "publisher":"Beatshapers",
           "product_code_ss":[
              "HACPARXQA"
           ],
           "excerpt":"Combatti orde di zombi in un'arena interattiva.",
           "internet":true,
           "nsuid_txt":[
              "70010000014431"
           ],
           "date_from":"2019-01-24T00:00:00Z",
           "language_availability":[
              "english"
           ],
           "price_has_discount_b":false,
           "price_discount_percentage_f":0.0,
           "title":"#KILLALLZOMBIES",
           "sorting_title":"#KILLALLZOMBIES",
           "gift_finder_carousel_image_url_s":"//cdn01.nintendo-europe.com/media/images/11_square_images/games_18/nintendo_switch_download_software/SQ_NSwitchDS_KillAllZombies_gift_finder_carousel.jpg",
           "wishlist_email_square_image_url_s":"//cdn01.nintendo-europe.com/media/images/11_square_images/games_18/nintendo_switch_download_software/SQ_NSwitchDS_KillAllZombies_square_image_wishlist.jpg",
           "players_to":2,
           "wishlist_email_banner640w_image_url_s":"//cdn01.nintendo-europe.com/media/images/10_share_images/games_15/nintendo_switch_download_software_1/H2x1_NSwitchDS_KillAllZombies_banner_image_wishlist_640w.jpg",
           "voice_chat_b":false,
           "playable_on_txt":[
              "HAC"
           ],
           "hits_i":300,
           "pretty_game_categories_txt":[
              "Azione",
              "Sparatutto"
           ],
           "gift_finder_wishlist_image_url_s":"//cdn01.nintendo-europe.com/media/images/11_square_images/games_18/nintendo_switch_download_software/SQ_NSwitchDS_KillAllZombies_gift_finder_wishlist.jpg",
           "switch_game_voucher_b":false,
           "game_category":[
              "shooter,action"
           ],
           "system_names_txt":[
              "Nintendo Switch"
           ],
           "pretty_agerating_s":"16",
           "price_regular_f":19.99,
           "eshop_removed_b":false,
           "players_from":1,
           "age_rating_type":"pegi",
           "price_sorting_f":19.99,
           "price_lowest_f":19.99,
           "age_rating_value":"16",
           "physical_version_b":false,
           "wishlist_email_banner460w_image_url_s":"//cdn01.nintendo-europe.com/media/images/10_share_images/games_15/nintendo_switch_download_software_1/H2x1_NSwitchDS_KillAllZombies_banner_image_wishlist_460w.jpg",
           "_version_":1664595832221990922,
           "popularity":857
        }
     ]
  }
}